paf_sapgui_eltrans/__init__.py
paf_sapgui_eltrans/al11.py
paf_sapgui_eltrans/bp.py
paf_sapgui_eltrans/cg3y.py
paf_sapgui_eltrans/cic.py
paf_sapgui_eltrans/jf01_2_3.py
paf_sapgui_eltrans/jf04.py
paf_sapgui_eltrans/jf06.py
paf_sapgui_eltrans/jfta.py
paf_sapgui_eltrans/jw25_26_27.py
paf_sapgui_eltrans/jw34_35_36.py
paf_sapgui_eltrans/sa38.py
paf_sapgui_eltrans/se16.py
paf_sapgui_eltrans/sm37.py
paf_sapgui_eltrans/sost.py
paf_sapgui_eltrans/zfmta_rar.py
paf_sapgui_eltrans/zjkta_ai_kd_rklsm.py
paf_sapgui_eltrans/zjkta_nb_rklsm.py
paf_sapgui_eltrans/zjkte_se.py
paf_sapgui_eltrans/zjvr_rjvnetch.py
paf_sapgui_eltrans-1.0.9.dist-info/WHEEL
paf_sapgui_eltrans-1.0.9.dist-info/METADATA
paf_sapgui_eltrans-1.0.9.dist-info/RECORD
