Metadata-Version: 2.1
Name: paf-sapgui-eltrans
Version: 1.0.9
Summary: 
Author: Your Name
Author-email: you@example.com
Requires-Python: >=3.10,<4.0
Classifier: Programming Language :: Python :: 3
Classifier: Programming Language :: Python :: 3.10
Requires-Dist: paf_sapgui (>=1.0.18,<2.0.0)
